checking/__init__.py
checking/__main__.py
checking/annotations.py
checking/asserts.py
checking/context.py
checking/exceptions.py
checking/runner.py
checking/classes/__init__.py
checking/classes/basic_case.py
checking/classes/basic_group.py
checking/classes/basic_suite.py
checking/classes/basic_test.py
checking/classes/common.py
checking/classes/data_file.py
checking/classes/exc_thread.py
checking/classes/fluent_assert.py
checking/classes/soft_assert.py
checking/classes/timer.py
checking/classes/listeners/__init__.py
checking/classes/listeners/basic.py
checking/classes/listeners/default.py
checking/classes/listeners/file_logger.py
checking/classes/mocking/__init__.py
checking/classes/mocking/calls.py
checking/classes/mocking/doubles.py
checking/classes/mocking/interfaces.py
checking/classes/mocking/stub.py
checking/classes/mocking/wrapper.py
checking/classes/mocking/write_wrapper.py
checking/helpers/__init__.py
checking/helpers/exception_traceback.py
checking/helpers/others.py
checking/helpers/report.py
checking-0.9.1.dist-info/LICENSE
checking-0.9.1.dist-info/METADATA
checking-0.9.1.dist-info/WHEEL
checking-0.9.1.dist-info/top_level.txt
checking-0.9.1.dist-info/RECORD
