Metadata-Version: 2.1
Name: checking
Version: 0.9.1
Summary: A small library for unit-testing
Home-page: https://github.com/kotolex/checking
Author: Lex Draven
Author-email: lexman2@yandex.ru
License: UNKNOWN
Platform: UNKNOWN
Classifier: Programming Language :: Python :: 3
Classifier: License :: OSI Approved :: MIT License
Classifier: Operating System :: OS Independent
Requires-Python: >=3.6
